tdx_proxy/__init__.py
tdx_proxy/tdx_proxy.py
motc_tdx_proxy-0.1.0.dist-info/LICENSE
motc_tdx_proxy-0.1.0.dist-info/METADATA
motc_tdx_proxy-0.1.0.dist-info/WHEEL
motc_tdx_proxy-0.1.0.dist-info/top_level.txt
motc_tdx_proxy-0.1.0.dist-info/RECORD
