Metadata-Version: 2.1
Name: motc-tdx-proxy
Version: 0.1.0
Summary: 台灣交通部「TDX運輸資料流通服務平臺」之python介接套件
Home-page: https://github.com/chihsuanwu/tdx-proxy
Author: Chi-Hsuan Wu
Author-email: chihsuanw@gmail.com
Project-URL: Bug Reports, https://github.com/chihsuanwu/tdx-proxy/issues
Project-URL: Source, https://github.com/chihsuanwu/tdx-proxy/
Keywords: tdx
Classifier: Intended Audience :: Developers
Classifier: License :: OSI Approved :: MIT License
Classifier: Operating System :: OS Independent
Classifier: Programming Language :: Python :: 3.10
Classifier: Programming Language :: Python :: 3.11
Classifier: Programming Language :: Python :: 3.12
Requires-Python: >=3.10, <4
License-File: LICENSE
Requires-Dist: requests
